numericnormalizer/__init__.py
numericnormalizer/core.py
numericnormalizer-0.1.0.dist-info/LICENSE
numericnormalizer-0.1.0.dist-info/METADATA
numericnormalizer-0.1.0.dist-info/WHEEL
numericnormalizer-0.1.0.dist-info/top_level.txt
numericnormalizer-0.1.0.dist-info/RECORD
