Metadata-Version: 2.1
Name: numericnormalizer
Version: 0.1.0
Summary: Converting number formats
Author: mattcoulter7 (Matt Coulter)
Author-email: <mattcoul7@gmail.com>
Keywords: python,nlp,numeric,sentence,language,convert,regex
Classifier: Development Status :: 1 - Planning
Classifier: Intended Audience :: Developers
Classifier: Programming Language :: Python :: 3
Classifier: Operating System :: Unix
Classifier: Operating System :: MacOS :: MacOS X
Classifier: Operating System :: Microsoft :: Windows
License-File: LICENSE
